setup.cfg
setup.py
tx/__init__.py
tx.tinymce_linguaplone_root_shortcut.egg-info/PKG-INFO
tx.tinymce_linguaplone_root_shortcut.egg-info/SOURCES.txt
tx.tinymce_linguaplone_root_shortcut.egg-info/dependency_links.txt
tx.tinymce_linguaplone_root_shortcut.egg-info/entry_points.txt
tx.tinymce_linguaplone_root_shortcut.egg-info/namespace_packages.txt
tx.tinymce_linguaplone_root_shortcut.egg-info/not-zip-safe
tx.tinymce_linguaplone_root_shortcut.egg-info/paster_plugins.txt
tx.tinymce_linguaplone_root_shortcut.egg-info/requires.txt
tx.tinymce_linguaplone_root_shortcut.egg-info/top_level.txt
tx/tinymce_linguaplone_root_shortcut/__init__.py
tx/tinymce_linguaplone_root_shortcut/configure.zcml
tx/tinymce_linguaplone_root_shortcut/shortcut.py
tx/tinymce_linguaplone_root_shortcut/tests.py