Metadata-Version: 1.1
Name: tx.tinymce-linguaplone-root-shortcut
Version: 1.0
Summary: Navigate to site root for language neutral content
Home-page: https://github.com/tuxwerk/tx.tinymce_linguaplone_root_shortcut
Author: Marek Kralewski
Author-email: mck@tuxwerk.de
License: GPL
Keywords: linguaplone tinymce neutral content
Platform: UNKNOWN
Classifier: Framework :: Plone
Classifier: Programming Language :: Python
